README
setup.cfg
setup.py
test/test_compile.py
test/test_mapuser.py
tiddlywebplugins/__init__.py
tiddlywebplugins/mapuser.py
tiddlywebplugins.mapuser.egg-info/PKG-INFO
tiddlywebplugins.mapuser.egg-info/SOURCES.txt
tiddlywebplugins.mapuser.egg-info/dependency_links.txt
tiddlywebplugins.mapuser.egg-info/namespace_packages.txt
tiddlywebplugins.mapuser.egg-info/not-zip-safe
tiddlywebplugins.mapuser.egg-info/requires.txt
tiddlywebplugins.mapuser.egg-info/top_level.txt