Metadata-Version: 1.0
Name: tiddlywebplugins.mapuser
Version: 0.1.0
Summary: Allows TiddlyWeb users to create alias usernames, deliberately without validation.
Home-page: http://pypi.python.org/pypi/tiddlywebplugins.mapuser
Author: Ben Paddock
Author-email: pads@thisispads.me.uk
License: UNKNOWN
Platform: Posix; MacOS X; Windows
